litegitpuller/__init__.py
litegitpuller/_version.py
litegitpuller-0.3.0.data/data/share/jupyter/labextensions/@jupyterlite/litegitpuller/package.json
litegitpuller-0.3.0.data/data/share/jupyter/labextensions/@jupyterlite/litegitpuller/static/389.08b22fc34e4e1261c9c7.js
litegitpuller-0.3.0.data/data/share/jupyter/labextensions/@jupyterlite/litegitpuller/static/747.be821cd0b51de1516504.js
litegitpuller-0.3.0.data/data/share/jupyter/labextensions/@jupyterlite/litegitpuller/static/remoteEntry.5da3ed293ba6a1285349.js
litegitpuller-0.3.0.data/data/share/jupyter/labextensions/@jupyterlite/litegitpuller/static/style.js
litegitpuller-0.3.0.data/data/share/jupyter/labextensions/@jupyterlite/litegitpuller/static/third-party-licenses.json
litegitpuller-0.3.0.data/data/share/jupyter/labextensions/@jupyterlite/litegitpuller/install.json
litegitpuller-0.3.0.dist-info/METADATA
litegitpuller-0.3.0.dist-info/WHEEL
litegitpuller-0.3.0.dist-info/licenses/LICENSE
litegitpuller-0.3.0.dist-info/RECORD
