Metadata-Version: 2.3
Name: litegitpuller
Version: 0.3.0
Dynamic: Keywords
Summary: A jupyterlite extension to automate cloning of a github repository.
Project-URL: Homepage, https://github.com/jupyterlite/litegitpuller
Project-URL: Bug Tracker, https://github.com/jupyterlite/litegitpuller/issues
Project-URL: Repository, https://github.com/jupyterlite/litegitpuller.git
Author-email: Jupyter Development Team <jupyter@googlegroups.com>
License: BSD 3-Clause License
Classifier: Framework :: Jupyter
Classifier: Framework :: Jupyter :: JupyterLab
Classifier: Framework :: Jupyter :: JupyterLab :: 4
Classifier: Framework :: Jupyter :: JupyterLab :: Extensions
Classifier: Framework :: Jupyter :: JupyterLab :: Extensions :: Prebuilt
Classifier: License :: OSI Approved :: BSD License
Classifier: Programming Language :: Python
Classifier: Programming Language :: Python :: 3
Classifier: Programming Language :: Python :: 3.8
Classifier: Programming Language :: Python :: 3.9
Classifier: Programming Language :: Python :: 3.10
Classifier: Programming Language :: Python :: 3.11
Classifier: Programming Language :: Python :: 3.12
Requires-Python: >=3.8
Provides-Extra: docs
Requires-Dist: jupyterlite-sphinx>=0.9.3; extra == 'docs'
Requires-Dist: jupyterlite-xeus-python<0.10.0,>=0.9.0; extra == 'docs'
Requires-Dist: myst-parser; extra == 'docs'
Requires-Dist: pydata-sphinx-theme; extra == 'docs'
Requires-Dist: sphinx>=4; extra == 'docs'
